test_travis/__init__.py
test_travis/__main__.py
test_travis/something.py
youtux.test_travis-1.0.0.dist-info/top_level.txt
youtux.test_travis-1.0.0.dist-info/entry_points.txt
youtux.test_travis-1.0.0.dist-info/METADATA
youtux.test_travis-1.0.0.dist-info/DESCRIPTION.rst
youtux.test_travis-1.0.0.dist-info/metadata.json
youtux.test_travis-1.0.0.dist-info/WHEEL
youtux.test_travis-1.0.0.dist-info/RECORD
