Metadata-Version: 2.0
Name: youtux.test-travis
Version: 1.0.0
Summary: Vanguard contains all the boilerplate you need to bootstrap a modern Python package.
Home-page: https://github.com/youtux/test-travis
Author: Alessio Bogon
Author-email: youtux@example.com
License: MIT
Keywords: t,e,s,t,-,t,r,a,v,i,s, ,d,e,v,e,l,o,p,m,e,n,t
Platform: UNKNOWN
Classifier: Development Status :: 3 - Alpha
Classifier: Intended Audience :: Developers
Classifier: Topic :: Software Development
Classifier: License :: OSI Approved :: MIT License
Classifier: Programming Language :: Python :: 2
Classifier: Programming Language :: Python :: 2.7
Classifier: Programming Language :: Python :: 3
Classifier: Programming Language :: Python :: 3.3
Classifier: Programming Language :: Python :: 3.4
Classifier: Environment :: Console
Requires-Dist: six
